[1,["d66ef8dd-7213-4f46-b40c-e3a9cac2a912@6c48a"],["_textureSource"],["cc.SpriteFrame"],0,[{"name":"d24","rect":{"x":0,"y":0,"width":202,"height":136},"offset":{"x":-1,"y":1.5},"originalSize":{"width":204,"height":139},"rotated":false,"capInsets":[0,0,0,0],"vertices":{"rawPosition":[-101,-68,0,101,-68,0,-101,68,0,101,68,0],"indexes":[0,1,2,2,1,3],"uv":[0,139,202,139,0,3,202,3],"nuv":[0,0.02158273381294964,0.9901960784313726,0.02158273381294964,0,1,0.9901960784313726,1],"minPos":{"x":-101,"y":-68,"z":0},"maxPos":{"x":101,"y":68,"z":0}},"packable":true,"pixelsToUnit":100,"pivot":{"x":0.5,"y":0.5},"meshType":0}],[0],0,[0],[0],[0]]
